timetables/parser/optivum/__init__.py
timetables/parser/optivum/cli.py
timetables/parser/optivum/parser.py
timetables/parser/optivum/utils.py
timetables_parser_optivum-1.0.0.dist-info/entry_points.txt
timetables_parser_optivum-1.0.0.dist-info/LICENSE
timetables_parser_optivum-1.0.0.dist-info/WHEEL
timetables_parser_optivum-1.0.0.dist-info/METADATA
timetables_parser_optivum-1.0.0.dist-info/RECORD
