Metadata-Version: 2.1
Name: timetables-parser-optivum
Version: 1.0.0
Summary: VULCAN® Optivum® timetable parser library
License: MIT
Author: Kuba Szczodrzyński
Author-email: kuba@szczodrzynski.pl
Requires-Python: >=3.8,<4.0
Classifier: License :: OSI Approved :: MIT License
Classifier: Programming Language :: Python :: 3
Classifier: Programming Language :: Python :: 3.10
Classifier: Programming Language :: Python :: 3.8
Classifier: Programming Language :: Python :: 3.9
Requires-Dist: aiohttp[speedups] (>=3.8.0,<4.0.0)
Requires-Dist: beautifulsoup4 (>=4.10.0,<5.0.0)
Requires-Dist: lxml (>=4.6.4,<5.0.0)
Requires-Dist: pydantic (>=1.8.2,<2.0.0)
Requires-Dist: timetables-lib (>=1.0.0,<2.0.0)
